__init__.py
algorithm_base.py
algorithmselector-1.1.0.dist-info/LICENSE
algorithmselector-1.1.0.dist-info/METADATA
algorithmselector-1.1.0.dist-info/WHEEL
algorithmselector-1.1.0.dist-info/RECORD
