Metadata-Version: 2.1
Name: AlgorithmSelector
Version: 1.1.0
Summary: A collection of various algorithms and data structures
Author: thomasthaddeus
Author-email: thaddeus.r.thomas@gmail.com
Requires-Python: >=3.11,<4.0
Classifier: Programming Language :: Python :: 3
Classifier: Programming Language :: Python :: 3.11
Classifier: Programming Language :: Python :: 3.12
Project-URL: repository, https://github.com/thomasthaddeus/AlgorithmSelector
